pulsar/__init__.py
pulsar/core.py
pulsar/locks.py
pulsar/main.py
pulsar/manager_endpoint_util.py
pulsar/manager_factory.py
pulsar/cache/__init__.py
pulsar/cache/persistence.py
pulsar/cache/util.py
pulsar/client/__init__.py
pulsar/client/action_mapper.py
pulsar/client/amqp_exchange.py
pulsar/client/amqp_exchange_factory.py
pulsar/client/client.py
pulsar/client/config_util.py
pulsar/client/container_job_config.py
pulsar/client/decorators.py
pulsar/client/destination.py
pulsar/client/exceptions.py
pulsar/client/job_directory.py
pulsar/client/manager.py
pulsar/client/object_client.py
pulsar/client/path_mapper.py
pulsar/client/relay_auth.py
pulsar/client/server_interface.py
pulsar/client/setup_handler.py
pulsar/client/util.py
pulsar/client/staging/__init__.py
pulsar/client/staging/down.py
pulsar/client/staging/up.py
pulsar/client/test/__init__.py
pulsar/client/test/check.py
pulsar/client/test/test_common.py
pulsar/client/test/test_relay_transport.py
pulsar/client/transport/__init__.py
pulsar/client/transport/curl.py
pulsar/client/transport/poster.py
pulsar/client/transport/relay.py
pulsar/client/transport/requests.py
pulsar/client/transport/ssh.py
pulsar/client/transport/standard.py
pulsar/client/transport/tus.py
pulsar/managers/__init__.py
pulsar/managers/queued.py
pulsar/managers/queued_cli.py
pulsar/managers/queued_condor.py
pulsar/managers/queued_drmaa.py
pulsar/managers/queued_drmaa_xsede.py
pulsar/managers/queued_external_drmaa.py
pulsar/managers/queued_pbs.py
pulsar/managers/stateful.py
pulsar/managers/status.py
pulsar/managers/unqueued.py
pulsar/managers/base/__init__.py
pulsar/managers/base/base_drmaa.py
pulsar/managers/base/directory.py
pulsar/managers/base/external.py
pulsar/managers/staging/__init__.py
pulsar/managers/staging/post.py
pulsar/managers/staging/pre.py
pulsar/managers/util/__init__.py
pulsar/managers/util/aws_batch.py
pulsar/managers/util/env.py
pulsar/managers/util/external.py
pulsar/managers/util/gcp_util.py
pulsar/managers/util/kill.py
pulsar_app-0.15.14.dist-info/licenses/LICENSE
pulsar_app-0.15.14.dist-info/METADATA
pulsar_app-0.15.14.dist-info/WHEEL
pulsar_app-0.15.14.dist-info/entry_points.txt
pulsar_app-0.15.14.dist-info/top_level.txt
pulsar_app-0.15.14.dist-info/RECORD
