Metadata-Version: 2.4
Name: pulsar-app
Version: 0.15.14
Summary: Distributed job execution application built for Galaxy (http://galaxyproject.org/).
Home-page: https://github.com/galaxyproject/pulsar
Author: Galaxy Project
Author-email: jmchilton@gmail.com
License: Apache License 2.0
Keywords: pulsar
Classifier: Development Status :: 5 - Production/Stable
Classifier: Intended Audience :: Developers
Classifier: Environment :: Console
Classifier: Operating System :: POSIX
Classifier: Operating System :: Microsoft :: Windows
Classifier: Natural Language :: English
Classifier: Programming Language :: Python :: 3
Classifier: Programming Language :: Python :: 3.6
Classifier: Programming Language :: Python :: 3.7
Classifier: Programming Language :: Python :: 3.8
Classifier: Programming Language :: Python :: 3.9
Classifier: Programming Language :: Python :: 3.10
Classifier: Programming Language :: Python :: 3.11
License-File: LICENSE
Requires-Dist: webob
Requires-Dist: psutil
Requires-Dist: PasteDeploy
Requires-Dist: pyyaml
Requires-Dist: galaxy-job-metrics>=21.9.0
Requires-Dist: galaxy-objectstore>=19.9.0
Requires-Dist: galaxy-tool-util>=19.9.0
Requires-Dist: galaxy-util>=22.1.2
Requires-Dist: paramiko
Requires-Dist: typing-extensions
Requires-Dist: pydantic-tes>=0.1.5
Requires-Dist: pyjwt
Requires-Dist: requests
Requires-Dist: tuspy
Requires-Dist: google-cloud-batch
Provides-Extra: amqp
Requires-Dist: kombu; extra == "amqp"
Provides-Extra: web
Requires-Dist: Paste; extra == "web"
Requires-Dist: PasteScript; extra == "web"
Provides-Extra: galaxy-extended-metadata
Requires-Dist: galaxy-job-execution; extra == "galaxy-extended-metadata"
Requires-Dist: galaxy-util[template]; extra == "galaxy-extended-metadata"
Dynamic: author
Dynamic: author-email
Dynamic: classifier
Dynamic: description
Dynamic: description-content-type
Dynamic: home-page
Dynamic: keywords
Dynamic: license
Dynamic: license-file
Dynamic: provides-extra
Dynamic: requires-dist
Dynamic: summary
